Workbook

Sheet Start here
A1: Mobilcab — 12-month organic marketing calendar
A2: From docs/Mobilcab_12_Month_Organic_Marketing_Calendar.md · Week 1 = month -6 · launch = week 27
B4: Settings
B6: Week 1 starts on (a Monday) | C6: 46307 | D6: Change this one date to move the whole plan, e.g. if the launch moves. Every date in the workbook follows it.
B7: Launch week | C7: 27 | D7: Fixed: the plan puts launch in week 27 (month -6 is weeks 1–4). Week labels L−26 … L+25 count from it.
B8: Launch date | C8: =C6+7*(C7-1) -> 46489 | D8: Calculated from the two cells above.
B10: How to use it
B11: Weekly plan | D11: The overview: one row per week, one column per platform, with a progress bar per week.
B12: Tasks | D12: The checklist: one row per task. Pick ✓ in the Done column when it's done. Done rows turn green; tasks whose week has passed without a ✓ turn red. Use the filter arrows to see one week or one platform.
B13: Weekly numbers | D13: Every Friday, fill in one row (the numbers come from Brevo, Plausible, Facebook and YouTube).
B14: Website steps | D14: When to flip each switch in src/site.ts, and what it needs first.
B15: Deadlines | D15: What has to be ready by which week. If one slips, move that week's announcement, not the trust-building around it.
B16: Content bank | D16: Post ideas. Note the week you use one.
B17: Routine | D17: The same short routine every week.
B19: Legend
B20: Yellow cell, blue text | D20: You fill this in (the start date, ✓ marks, notes, weekly numbers).
B21: Green row | D21: Task done.
B22: Red row | D22: Its week is over and it has no ✓ yet.
B23: [VERIFY] | D23: A date or fact to confirm before relying on it (holidays, trade-show dates, app features).
B25: Time budget | D25: If time runs short, cut the blog first, then social posting. Never cut Facebook group presence or customer support (Marketing Plan Section 11).

Sheet Weekly plan
A1: Weekly plan
A2: Progress counts the ✓ marks on the Tasks sheet. Dates follow the start date on "Start here".
A4: Week | B4: Label | C4: Week starts | D4: Phase | E4: Focus | F4: Hours | G4: Facebook groups | H4: Facebook Page | I4: YouTube | J4: Blog | K4: Email | L4: Website | M4: Other (offline, LinkedIn, beta, admin…) | N4: Tasks | O4: Done | P4: Progress
A5: 1 | B5: ="L"&IF(A5-'Start here'!$C$7<0,"−","+")&ABS(A5-'Start here'!$C$7) -> L−26 | C5: ='Start here'!$C$6+7*(A5-1) -> 46307 | D5: Month -6 · Quiet foundation | E5: Set up the foundations | F5: 10–12 h | H5: • Create the Page: name, wordmark logo, cover, one-line description, link. No posts yet | I5: • Create the channel (profile only, no videos yet) | L5: • Deploy the coming-soon page (Git/GitHub, Vercel, domain, Brevo, Plausible: see README) | M5: • Admin: Start SRL registration, Stripe account and e-Factura invoicing (Marketing Plan 4b) • Research: List 10–15 groups (search: tâmplari, mobilă la comandă, CNC lemn, proiectare mobilă) | N5: =COUNTIF(Tasks!$A:$A,A5) -> 6 | O5: =COUNTIFS(Tasks!$A:$A,A5,Tasks!$F:$F,"✓") -> 0 | P5: =IF(N5=0,"",O5/N5) -> 0
A6: 2 | B6: ="L"&IF(A6-'Start here'!$C$7<0,"−","+")&ABS(A6-'Start here'!$C$7) -> L−25 | C6: ='Start here'!$C$6+7*(A6-1) -> 46314 | D6: Month -6 · Quiet foundation | E6: Join the groups | F6: 10–12 h | G6: • Join the 5–10 best groups; read each group's rules (links allowed? project mentions?) • Start the question log: every question carpenters ask, word for word | M6: • Legal: Send the Privacy Policy and Terms drafts to the lawyer (Privacy approval needed by week 12) | N6: =COUNTIF(Tasks!$A:$A,A6) -> 4 | O6: =COUNTIFS(Tasks!$A:$A,A6,Tasks!$F:$F,"✓") -> 0 | P6: =IF(N6=0,"",O6/N6) -> 0
A7: 3 | B7: ="L"&IF(A7-'Start here'!$C$7<0,"−","+")&ABS(A7-'Start here'!$C$7) -> L−24 | C7: ='Start here'!$C$6+7*(A7-1) -> 46321 | D7: Month -6 · Quiet foundation | E7: Observe | F7: 10–12 h | G7: • Observe only: tone, recurring pain points, respected voices (anchor-customer candidates) | M7: • Content: Write 8–10 trade tips for the content bank | N7: =COUNTIF(Tasks!$A:$A,A7) -> 3 | O7: =COUNTIFS(Tasks!$A:$A,A7,Tasks!$F:$F,"✓") -> 0 | P7: =IF(N7=0,"",O7/N7) -> 0
A8: 4 | B8: ="L"&IF(A8-'Start here'!$C$7<0,"−","+")&ABS(A8-'Start here'!$C$7) -> L−23 | C8: ='Start here'!$C$6+7*(A8-1) -> 46328 | D8: Month -6 · Quiet foundation | E8: Plan the offline side | F8: 10–12 h | M8: • Research: Find APMR and regional wood-cluster contacts • Research: Look up 2027 dates for BIFE-SIM and regional fairs [VERIFY] • Review: Monthly review: confirmed sign-ups, confirmation rate | N8: =COUNTIF(Tasks!$A:$A,A8) -> 4 | O8: =COUNTIFS(Tasks!$A:$A,A8,Tasks!$F:$F,"✓") -> 0 | P8: =IF(N8=0,"",O8/N8) -> 0
A9: 5 | B9: ="L"&IF(A9-'Start here'!$C$7<0,"−","+")&ABS(A9-'Start here'!$C$7) -> L−22 | C9: ='Start here'!$C$6+7*(A9-1) -> 46335 | D9: Month -5 · Trust-building | E9: Start helping | F9: 10–12 h | G9: • Answer 3–5 real questions properly, no self-promotion; update the question log | H9: • First post: trade tip ("Cum calculezi lățimea polițelor între laterale") | M9: • Anchor customer: Keep talking with the 2–3 candidates as a peer, no pitch | N9: =COUNTIF(Tasks!$A:$A,A9) -> 4 | O9: =COUNTIFS(Tasks!$A:$A,A9,Tasks!$F:$F,"✓") -> 0 | P9: =IF(N9=0,"",O9/N9) -> 0
A10: 6 | B10: ="L"&IF(A10-'Start here'!$C$7<0,"−","+")&ABS(A10-'Start here'!$C$7) -> L−21 | C10: ='Start here'!$C$6+7*(A10-1) -> 46342 | D10: Month -5 · Trust-building | E10: First video, first association contact | F10: 10–12 h | G10: • Answer 3–5 real questions properly, no self-promotion; update the question log | I10: • First short video (2–4 min): a generic trade tip, not about the app | M10: • Associations: Introductory email to APMR (learning, not pitching) • Anchor customer: Keep talking with the 2–3 candidates as a peer, no pitch | N10: =COUNTIF(Tasks!$A:$A,A10) -> 5 | O10: =COUNTIFS(Tasks!$A:$A,A10,Tasks!$F:$F,"✓") -> 0 | P10: =IF(N10=0,"",O10/N10) -> 0
A11: 7 | B11: ="L"&IF(A11-'Start here'!$C$7<0,"−","+")&ABS(A11-'Start here'!$C$7) -> L−20 | C11: ='Start here'!$C$6+7*(A11-1) -> 46349 | D11: Month -5 · Trust-building | E11: Validate price and free plan | F11: 10–12 h | G11: • Answer 3–5 real questions properly, no self-promotion; update the question log | H11: • Trade tip #2 | M11: • Validation: Ask 5–10 people privately what would make them try a new tool, what they use, a fair monthly price (Marketing Plan 3b) • Anchor customer: Keep talking with the 2–3 candidates as a peer, no pitch | N11: =COUNTIF(Tasks!$A:$A,A11) -> 5 | O11: =COUNTIFS(Tasks!$A:$A,A11,Tasks!$F:$F,"✓") -> 0 | P11: =IF(N11=0,"",O11/N11) -> 0
A12: 8 | B12: ="L"&IF(A12-'Start here'!$C$7<0,"−","+")&ABS(A12-'Start here'!$C$7) -> L−19 | C12: ='Start here'!$C$6+7*(A12-1) -> 46356 | D12: Month -5 · Trust-building | E12: Workshop visits (1 Dec: National Day) | F12: 10–12 h | G12: • Answer 3–5 real questions properly, no self-promotion; update the question log | M12: • Offline: Visit 2–3 local workshops (with permission) and watch how they design and cut • Anchor customer: Keep talking with the 2–3 candidates as a peer, no pitch • Review: Monthly review | N12: =COUNTIF(Tasks!$A:$A,A12) -> 5 | O12: =COUNTIFS(Tasks!$A:$A,A12,Tasks!$F:$F,"✓") -> 0 | P12: =IF(N12=0,"",O12/N12) -> 0
A13: 9 | B13: ="L"&IF(A13-'Start here'!$C$7<0,"−","+")&ABS(A13-'Start here'!$C$7) -> L−18 | C13: ='Start here'!$C$6+7*(A13-1) -> 46363 | D13: Month -4 · Soft mentions + referrals | E13: First soft mentions | F13: 8–12 h | G13: • Keep answering; where relevant and allowed, mention "lucrez chiar la ceva pentru problema asta" in a comment (no link unless asked) | H13: • First behind-the-scenes post: a WIP screenshot | N13: =COUNTIF(Tasks!$A:$A,A13) -> 3 | O13: =COUNTIFS(Tasks!$A:$A,A13,Tasks!$F:$F,"✓") -> 0 | P13: =IF(N13=0,"",O13/N13) -> 0
A14: 10 | B14: ="L"&IF(A14-'Start here'!$C$7<0,"−","+")&ABS(A14-'Start here'!$C$7) -> L−17 | C14: ='Start here'!$C$6+7*(A14-1) -> 46370 | D14: Month -4 · Soft mentions + referrals | E14: First build log | F14: 8–12 h | G14: • Keep answering questions (never stop this) | H14: • Behind the scenes: WIP #2 | K14: • First monthly build log ("jurnal de construcție") to the confirmed waitlist: 150–250 words + a screenshot | N14: =COUNTIF(Tasks!$A:$A,A14) -> 4 | O14: =COUNTIFS(Tasks!$A:$A,A14,Tasks!$F:$F,"✓") -> 0 | P14: =IF(N14=0,"",O14/N14) -> 0
A15: 11 | B15: ="L"&IF(A15-'Start here'!$C$7<0,"−","+")&ABS(A15-'Start here'!$C$7) -> L−16 | C15: ='Start here'!$C$6+7*(A15-1) -> 46377 | D15: Month -4 · Soft mentions + referrals | E15: Holidays (Christmas): no announcements | F15: 8–12 h | G15: • Replies only | H15: • One light seasonal post | M15: • Prep: Lawyer approval of the Privacy Policy; fill in EMAIL_SETTINGS; rebuild the emails | N15: =COUNTIF(Tasks!$A:$A,A15) -> 4 | O15: =COUNTIFS(Tasks!$A:$A,A15,Tasks!$F:$F,"✓") -> 0 | P15: =IF(N15=0,"",O15/N15) -> 0
A16: 12 | B16: ="L"&IF(A16-'Start here'!$C$7<0,"−","+")&ABS(A16-'Start here'!$C$7) -> L−15 | C16: ='Start here'!$C$6+7*(A16-1) -> 46384 | D16: Month -4 · Soft mentions + referrals | E16: Holidays (New Year): no announcements | F16: 8–12 h | G16: • Replies only | M16: • Prep: Get week 13 ready: npm run test:all, check-launch, draft the invite-program posts | N16: =COUNTIF(Tasks!$A:$A,A16) -> 3 | O16: =COUNTIFS(Tasks!$A:$A,A16,Tasks!$F:$F,"✓") -> 0 | P16: =IF(N16=0,"",O16/N16) -> 0
A17: 13 | B17: ="L"&IF(A17-'Start here'!$C$7<0,"−","+")&ABS(A17-'Start here'!$C$7) -> L−14 | C17: ='Start here'!$C$6+7*(A17-1) -> 46391 | D17: Month -4 · Soft mentions + referrals | E17: REFERRAL LAUNCH | F17: 8–12 h | G17: • At most one own value-led post per group this month, only where allowed | H17: • Announce the invite program; pin it | K17: • New-year update + invite program: 3 confirmed invites = a guaranteed private-beta place | L17: • Publish Home + Privacy; REFERRAL_PROGRAM = true; rebuild + re-paste the emails; deploy | M17: • WhatsApp: Share your own invite link with carpenters you know personally | N17: =COUNTIF(Tasks!$A:$A,A17) -> 6 | O17: =COUNTIFS(Tasks!$A:$A,A17,Tasks!$F:$F,"✓") -> 0 | P17: =IF(N17=0,"",O17/N17) -> 0
A18: 14 | B18: ="L"&IF(A18-'Start here'!$C$7<0,"−","+")&ABS(A18-'Start here'!$C$7) -> L−13 | C18: ='Start here'!$C$6+7*(A18-1) -> 46398 | D18: Month -3 · Private beta | E18: Choose the beta testers | F18: 12–14 h | G18: • Keep answering questions (never stop this) | K18: • Build log #2: the private beta has started | M18: • Beta: Pick 15–20 testers (everyone with 3+ confirmed invites, the anchor customer, the warmest contacts); invite each personally | N18: =COUNTIF(Tasks!$A:$A,A18) -> 4 | O18: =COUNTIFS(Tasks!$A:$A,A18,Tasks!$F:$F,"✓") -> 0 | P18: =IF(N18=0,"",O18/N18) -> 0
A19: 15 | B19: ="L"&IF(A19-'Start here'!$C$7<0,"−","+")&ABS(A19-'Start here'!$C$7) -> L−12 | C19: ='Start here'!$C$6+7*(A19-1) -> 46405 | D19: Month -3 · Private beta | E19: Private beta: onboarding | F19: 12–14 h | G19: • Keep answering questions (never stop this) | H19: • Behind the scenes: what we learned in the beta (with permission) | M19: • Beta: 5–7 one-to-one onboarding sessions (~45 min); ask permission to record and to quote | N19: =COUNTIF(Tasks!$A:$A,A19) -> 4 | O19: =COUNTIFS(Tasks!$A:$A,A19,Tasks!$F:$F,"✓") -> 0 | P19: =IF(N19=0,"",O19/N19) -> 0
A20: 16 | B20: ="L"&IF(A20-'Start here'!$C$7<0,"−","+")&ABS(A20-'Start here'!$C$7) -> L−11 | C20: ='Start here'!$C$6+7*(A20-1) -> 46412 | D20: Month -3 · Private beta | E20: FOUNDING PARTNER RESERVATIONS OPEN | F20: 12–14 h | G20: • Keep answering questions (never stop this) | H20: • Founding Partner program post (co-creation framing) | K20: • 100 Founding Partner spots: reserve now, nothing to pay | L20: • Publish the Founding Partner page (set BREVO_FP_LIST_ID first) | M20: • Beta: 5–7 one-to-one onboarding sessions (~45 min); ask permission to record and to quote | N20: =COUNTIF(Tasks!$A:$A,A20) -> 6 | O20: =COUNTIFS(Tasks!$A:$A,A20,Tasks!$F:$F,"✓") -> 0 | P20: =IF(N20=0,"",O20/N20) -> 0
A21: 17 | B21: ="L"&IF(A21-'Start here'!$C$7<0,"−","+")&ABS(A21-'Start here'!$C$7) -> L−10 | C21: ='Start here'!$C$6+7*(A21-1) -> 46419 | D21: Month -3 · Private beta | E21: Private beta: onboarding | F21: 12–14 h | G21: • Keep answering questions (never stop this) | H21: • Behind the scenes: beta update | M21: • Beta: 5–7 one-to-one onboarding sessions (~45 min); ask permission to record and to quote • Review: Monthly review: reservations, beta activation (first export), feedback themes | N21: =COUNTIF(Tasks!$A:$A,A21) -> 5 | O21: =COUNTIFS(Tasks!$A:$A,A21,Tasks!$F:$F,"✓") -> 0 | P21: =IF(N21=0,"",O21/N21) -> 0
A22: 18 | B22: ="L"&IF(A22-'Start here'!$C$7<0,"−","+")&ABS(A22-'Start here'!$C$7) -> L−9 | C22: ='Start here'!$C$6+7*(A22-1) -> 46426 | D22: Month -2 · Proof building | E22: Demo 1 + blog post 1 | F22: 12 h | G22: • Link the blog post in a comment where a question matches | I22: • Record demo 1 (design flow) on a real beta project (Launch Content Kit 2.1) | J22: • Publish post 1 "Program proiectare mobilă gratuit…" after verifying competitor facts (blog: true) | K22: • Build log #3 | N22: =COUNTIF(Tasks!$A:$A,A22) -> 5 | O22: =COUNTIFS(Tasks!$A:$A,A22,Tasks!$F:$F,"✓") -> 0 | P22: =IF(N22=0,"",O22/N22) -> 0
A23: 19 | B23: ="L"&IF(A23-'Start here'!$C$7<0,"−","+")&ABS(A23-'Start here'!$C$7) -> L−8 | C23: ='Start here'!$C$6+7*(A23-1) -> 46433 | D23: Month -2 · Proof building | E23: Demo 2 + blog post 2 | F23: 12 h | G23: • Keep answering questions (never stop this) | I23: • Record demo 2 (AI assistant, Kit 2.2) | J23: • Publish post 2 "Cum faci cutlist pentru CNC…" | N23: =COUNTIF(Tasks!$A:$A,A23) -> 4 | O23: =COUNTIFS(Tasks!$A:$A,A23,Tasks!$F:$F,"✓") -> 0 | P23: =IF(N23=0,"",O23/N23) -> 0
A24: 20 | B24: ="L"&IF(A24-'Start here'!$C$7<0,"−","+")&ABS(A24-'Start here'!$C$7) -> L−7 | C24: ='Start here'!$C$6+7*(A24-1) -> 46440 | D24: Month -2 · Proof building | E24: Demo 3 + blog post 3 + Demo page | F24: 12 h | G24: • Keep answering questions (never stop this) | I24: • Record demo 3 (cutlist/CNC export, Kit 2.3); upload all three | J24: • Publish post 3 "Polyboard vs. alternative cloud-based" | L24: • Publish the Demo page; add the video IDs to src/data/demoVideos.ts | N24: =COUNTIF(Tasks!$A:$A,A24) -> 5 | O24: =COUNTIFS(Tasks!$A:$A,A24,Tasks!$F:$F,"✓") -> 0 | P24: =IF(N24=0,"",O24/N24) -> 0
A25: 21 | B25: ="L"&IF(A25-'Start here'!$C$7<0,"−","+")&ABS(A25-'Start here'!$C$7) -> L−6 | C25: ='Start here'!$C$6+7*(A25-1) -> 46447 | D25: Month -2 · Proof building | E25: Social proof | F25: 12 h | G25: • First demo-clip post in 1–2 groups where you're well known | H25: • Testimonial post #1 (tag the tester if they agree) | L25: • Publish the FAQ; add 3–5 real testimonials to src/data/testimonials.ts | N25: =COUNTIF(Tasks!$A:$A,A25) -> 4 | O25: =COUNTIFS(Tasks!$A:$A,A25,Tasks!$F:$F,"✓") -> 0 | P25: =IF(N25=0,"",O25/N25) -> 0
A26: 22 | B26: ="L"&IF(A26-'Start here'!$C$7<0,"−","+")&ABS(A26-'Start here'!$C$7) -> L−5 | C26: ='Start here'!$C$6+7*(A26-1) -> 46454 | D26: Month -2 · Proof building | E26: Final decisions | F26: 12 h | G26: • Keep answering questions (never stop this) | M26: • Decide: Final prices, free-plan limits, Founding Partner terms (open questions in DECISIONS.md) • Review: Monthly review | N26: =COUNTIF(Tasks!$A:$A,A26) -> 4 | O26: =COUNTIFS(Tasks!$A:$A,A26,Tasks!$F:$F,"✓") -> 0 | P26: =IF(N26=0,"",O26/N26) -> 0
A27: 23 | B27: ="L"&IF(A27-'Start here'!$C$7<0,"−","+")&ABS(A27-'Start here'!$C$7) -> L−4 | C27: ='Start here'!$C$6+7*(A27-1) -> 46461 | D27: Month -1 · Countdown | E27: Countdown: 4 weeks | F27: 12–14 h | G27: • Keep answering questions (never stop this) | H27: • Countdown #1 ("4 săptămâni") | K27: • Launch date announced: "Pe 12 aprilie lansăm" | L27: • Publish Pricing + Terms (lawyer-approved) | M27: • Anchor customer: Agree how they'll take part at launch • Development: Stripe payments working (make a test payment) | N27: =COUNTIF(Tasks!$A:$A,A27) -> 7 | O27: =COUNTIFS(Tasks!$A:$A,A27,Tasks!$F:$F,"✓") -> 0 | P27: =IF(N27=0,"",O27/N27) -> 0
A28: 24 | B28: ="L"&IF(A28-'Start here'!$C$7<0,"−","+")&ABS(A28-'Start here'!$C$7) -> L−3 | C28: ='Start here'!$C$6+7*(A28-1) -> 46468 | D28: Month -1 · Countdown | E28: Countdown: 3 weeks | F28: 12–14 h | G28: • Value post with the launch date at the end, where allowed | H28: • Countdown #2: a short demo clip | I28: • Tutorial #2 (from the question log) | N28: =COUNTIF(Tasks!$A:$A,A28) -> 4 | O28: =COUNTIFS(Tasks!$A:$A,A28,Tasks!$F:$F,"✓") -> 0 | P28: =IF(N28=0,"",O28/N28) -> 0
A29: 25 | B29: ="L"&IF(A29-'Start here'!$C$7<0,"−","+")&ABS(A29-'Start here'!$C$7) -> L−2 | C29: ='Start here'!$C$6+7*(A29-1) -> 46475 | D29: Month -1 · Countdown | E29: Countdown: 2 weeks | F29: 12–14 h | G29: • Keep answering questions (never stop this) | H29: • Countdown #3: a testimonial | M29: • Launch prep: Finalise the founder-story post for each group (Launch Content Kit 3.1) • Support: Answers ready for the 5–10 most likely questions | N29: =COUNTIF(Tasks!$A:$A,A29) -> 5 | O29: =COUNTIFS(Tasks!$A:$A,A29,Tasks!$F:$F,"✓") -> 0 | P29: =IF(N29=0,"",O29/N29) -> 0
A30: 26 | B30: ="L"&IF(A30-'Start here'!$C$7<0,"−","+")&ABS(A30-'Start here'!$C$7) -> L−1 | C30: ='Start here'!$C$6+7*(A30-1) -> 46482 | D30: Month -1 · Countdown | E30: Countdown: next week | F30: 12–14 h | G30: • Keep answering questions (never stop this) | H30: • Countdown #4 ("săptămâna viitoare") | K30: • Launching next week + Founding Partner spots left | L30: • Final checks: npm run test:all, check-launch, a test payment, every Brevo email | N30: =COUNTIF(Tasks!$A:$A,A30) -> 5 | O30: =COUNTIFS(Tasks!$A:$A,A30,Tasks!$F:$F,"✓") -> 0 | P30: =IF(N30=0,"",O30/N30) -> 0
A31: 27 | B31: ="L"&IF(A31-'Start here'!$C$7<0,"−","+")&ABS(A31-'Start here'!$C$7) -> L+0 | C31: ='Start here'!$C$6+7*(A31-1) -> 46489 | D31: Launch month | E31: LAUNCH | F31: ~20 h | G31: • Founder-story post in each group, spread over the day, adapted per group (link in the comments) | H31: • Founder-story post, pinned | K31: • To the whole waitlist: "Mobilcab e live — locurile Founding Partner sunt deschise" | L31: • Day 1: productPublic = true; deploy; Founding Partner payments live | M31: • Anchor customer: Comments and shares • Support: Reply to every comment and message the same day | N31: =COUNTIF(Tasks!$A:$A,A31) -> 7 | O31: =COUNTIFS(Tasks!$A:$A,A31,Tasks!$F:$F,"✓") -> 0 | P31: =IF(N31=0,"",O31/N31) -> 0
A32: 28 | B32: ="L"&IF(A32-'Start here'!$C$7<0,"−","+")&ABS(A32-'Start here'!$C$7) -> L+1 | C32: ='Start here'!$C$6+7*(A32-1) -> 46496 | D32: Launch month | E32: Launch follow-up | F32: ~20 h | G32: • Replies only | H32: • First real user project (with permission) | I32: • "Răspund la întrebările voastre" video from launch-week questions | M32: • Onboarding: Concierge sessions for new Founding Partners | N32: =COUNTIF(Tasks!$A:$A,A32) -> 5 | O32: =COUNTIFS(Tasks!$A:$A,A32,Tasks!$F:$F,"✓") -> 0 | P32: =IF(N32=0,"",O32/N32) -> 0
A33: 29 | B33: ="L"&IF(A33-'Start here'!$C$7<0,"−","+")&ABS(A33-'Start here'!$C$7) -> L+2 | C33: ='Start here'!$C$6+7*(A33-1) -> 46503 | D33: Launch month | E33: Transparency | F33: ~20 h | G33: • Replies only; don't re-post the launch | H33: • "What we fixed in week 1" post | N33: =COUNTIF(Tasks!$A:$A,A33) -> 3 | O33: =COUNTIFS(Tasks!$A:$A,A33,Tasks!$F:$F,"✓") -> 0 | P33: =IF(N33=0,"",O33/N33) -> 0
A34: 30 | B34: ="L"&IF(A34-'Start here'!$C$7<0,"−","+")&ABS(A34-'Start here'!$C$7) -> L+3 | C34: ='Start here'!$C$6+7*(A34-1) -> 46510 | D34: Launch month | E34: Light week (1 May; Orthodox Easter 2 May [VERIFY]) | F34: ~20 h | H34: • One post | M34: • Review: Launch-month review: sign-ups, Founding Partners, activation, top questions | N34: =COUNTIF(Tasks!$A:$A,A34) -> 3 | O34: =COUNTIFS(Tasks!$A:$A,A34,Tasks!$F:$F,"✓") -> 0 | P34: =IF(N34=0,"",O34/N34) -> 0
A35: 31 | B35: ="L"&IF(A35-'Start here'!$C$7<0,"−","+")&ABS(A35-'Start here'!$C$7) -> L+4 | C35: ='Start here'!$C$6+7*(A35-1) -> 46517 | D35: Phase 1 · Romania growth | E35: First changelog | F35: 8–10 h | G35: • Answer questions (about 2 h) | H35: • 2 posts this week | I35: • Tutorial #3 | J35: • Post 4, from the most common question in the log | K35: • First monthly changelog to paying users (Marketing Plan 6a) | N35: =COUNTIF(Tasks!$A:$A,A35) -> 6 | O35: =COUNTIFS(Tasks!$A:$A,A35,Tasks!$F:$F,"✓") -> 0 | P35: =IF(N35=0,"",O35/N35) -> 0
A36: 32 | B36: ="L"&IF(A36-'Start here'!$C$7<0,"−","+")&ABS(A36-'Start here'!$C$7) -> L+5 | C36: ='Start here'!$C$6+7*(A36-1) -> 46524 | D36: Phase 1 · Romania growth | E36: Case study #1 | F36: 8–10 h | G36: • Answer questions (about 2 h) | H36: • 2 posts this week | M36: • Case study: Case study #1 with the anchor customer (project, time saved) | N36: =COUNTIF(Tasks!$A:$A,A36) -> 4 | O36: =COUNTIFS(Tasks!$A:$A,A36,Tasks!$F:$F,"✓") -> 0 | P36: =IF(N36=0,"",O36/N36) -> 0
A37: 33 | B37: ="L"&IF(A37-'Start here'!$C$7<0,"−","+")&ABS(A37-'Start here'!$C$7) -> L+6 | C37: ='Start here'!$C$6+7*(A37-1) -> 46531 | D37: Phase 1 · Romania growth | E37: Publish case study #1 | F37: 8–10 h | G37: • Share case study #1 where relevant; answer questions | H37: • Publish case study #1 (+1 more post) | N37: =COUNTIF(Tasks!$A:$A,A37) -> 3 | O37: =COUNTIFS(Tasks!$A:$A,A37,Tasks!$F:$F,"✓") -> 0 | P37: =IF(N37=0,"",O37/N37) -> 0
A38: 34 | B38: ="L"&IF(A38-'Start here'!$C$7<0,"−","+")&ABS(A38-'Start here'!$C$7) -> L+7 | C38: ='Start here'!$C$6+7*(A38-1) -> 46538 | D38: Phase 1 · Romania growth | E38: Offline | F38: 8–10 h | G38: • Answer questions (about 2 h) | H38: • 2 posts this week | M38: • Offline: A regional fair, or 3 workshop visits with a tablet demo | N38: =COUNTIF(Tasks!$A:$A,A38) -> 4 | O38: =COUNTIFS(Tasks!$A:$A,A38,Tasks!$F:$F,"✓") -> 0 | P38: =IF(N38=0,"",O38/N38) -> 0
A39: 35 | B39: ="L"&IF(A39-'Start here'!$C$7<0,"−","+")&ABS(A39-'Start here'!$C$7) -> L+8 | C39: ='Start here'!$C$6+7*(A39-1) -> 46545 | D39: Phase 1 · Romania growth | E39: Newsletter | F39: 8–10 h | G39: • Answer questions (about 2 h) | H39: • 2 posts this week | I39: • Tutorial #4 | K39: • Monthly newsletter to free users and the waitlist | N39: =COUNTIF(Tasks!$A:$A,A39) -> 5 | O39: =COUNTIFS(Tasks!$A:$A,A39,Tasks!$F:$F,"✓") -> 0 | P39: =IF(N39=0,"",O39/N39) -> 0
A40: 36 | B40: ="L"&IF(A40-'Start here'!$C$7<0,"−","+")&ABS(A40-'Start here'!$C$7) -> L+9 | C40: ='Start here'!$C$6+7*(A40-1) -> 46552 | D40: Phase 1 · Romania growth | E40: Retention | F40: 8–10 h | G40: • Answer questions (about 2 h) | H40: • 2 posts this week | M40: • Retention: Personal "need help?" message to paying users inactive for 14+ days (6a) | N40: =COUNTIF(Tasks!$A:$A,A40) -> 4 | O40: =COUNTIFS(Tasks!$A:$A,A40,Tasks!$F:$F,"✓") -> 0 | P40: =IF(N40=0,"",O40/N40) -> 0
A41: 37 | B41: ="L"&IF(A41-'Start here'!$C$7<0,"−","+")&ABS(A41-'Start here'!$C$7) -> L+10 | C41: ='Start here'!$C$6+7*(A41-1) -> 46559 | D41: Phase 1 · Romania growth | E41: Blog + testimonial (Rusalii 20–21 June [VERIFY]) | F41: 8–10 h | G41: • Answer questions (about 2 h) | H41: • Testimonial #2 (+1 more post) | J41: • Post 5 | N41: =COUNTIF(Tasks!$A:$A,A41) -> 4 | O41: =COUNTIFS(Tasks!$A:$A,A41,Tasks!$F:$F,"✓") -> 0 | P41: =IF(N41=0,"",O41/N41) -> 0
A42: 38 | B42: ="L"&IF(A42-'Start here'!$C$7<0,"−","+")&ABS(A42-'Start here'!$C$7) -> L+11 | C42: ='Start here'!$C$6+7*(A42-1) -> 46566 | D42: Phase 1 · Romania growth | E42: Founding Partner check-ins | F42: 8–10 h | G42: • Answer questions (about 2 h) | H42: • 2 posts this week | M42: • Retention: Quarterly check-in with every Founding Partner (6a) | N42: =COUNTIF(Tasks!$A:$A,A42) -> 4 | O42: =COUNTIFS(Tasks!$A:$A,A42,Tasks!$F:$F,"✓") -> 0 | P42: =IF(N42=0,"",O42/N42) -> 0
A43: 39 | B43: ="L"&IF(A43-'Start here'!$C$7<0,"−","+")&ABS(A43-'Start here'!$C$7) -> L+12 | C43: ='Start here'!$C$6+7*(A43-1) -> 46573 | D43: Phase 1 · Romania growth | E43: Phase 1 review | F43: 8–10 h | G43: • Answer questions (about 2 h) | H43: • 2 posts this week | M43: • Review: Phase 1 review vs goal: 100–300 users, 10–30 paying Founding Partners, 2–3 case studies | N43: =COUNTIF(Tasks!$A:$A,A43) -> 4 | O43: =COUNTIFS(Tasks!$A:$A,A43,Tasks!$F:$F,"✓") -> 0 | P43: =IF(N43=0,"",O43/N43) -> 0
A44: 40 | B44: ="L"&IF(A44-'Start here'!$C$7<0,"−","+")&ABS(A44-'Start here'!$C$7) -> L+13 | C44: ='Start here'!$C$6+7*(A44-1) -> 46580 | D44: Phase 2 · New segments | E44: Start Phase 2: LinkedIn + designers | F44: 8–10 h | G44: • Answer questions (about 2 h) | H44: • 2 posts this week | M44: • LinkedIn: Company page + refreshed founder profile • Groups: Join designer/architect groups (Facebook + LinkedIn); observe 2–3 weeks | N44: =COUNTIF(Tasks!$A:$A,A44) -> 5 | O44: =COUNTIFS(Tasks!$A:$A,A44,Tasks!$F:$F,"✓") -> 0 | P44: =IF(N44=0,"",O44/N44) -> 0
A45: 41 | B45: ="L"&IF(A45-'Start here'!$C$7<0,"−","+")&ABS(A45-'Start here'!$C$7) -> L+14 | C45: ='Start here'!$C$6+7*(A45-1) -> 46587 | D45: Phase 2 · New segments | E45: Case study #2 | F45: 8–10 h | G45: • Answer questions (about 2 h) | H45: • 2 posts this week | M45: • Case study: Case study #2 • Designers: Client-presentation angle, only if the app really shares live designs [VERIFY] | N45: =COUNTIF(Tasks!$A:$A,A45) -> 5 | O45: =COUNTIFS(Tasks!$A:$A,A45,Tasks!$F:$F,"✓") -> 0 | P45: =IF(N45=0,"",O45/N45) -> 0
A46: 42 | B46: ="L"&IF(A46-'Start here'!$C$7<0,"−","+")&ABS(A46-'Start here'!$C$7) -> L+15 | C46: ='Start here'!$C$6+7*(A46-1) -> 46594 | D46: Phase 2 · New segments | E46: Design schools | F46: 8–10 h | G46: • Answer questions (about 2 h) | H46: • 2 posts this week | M46: • Partnerships: Contact 1–2 design schools about an autumn webinar | N46: =COUNTIF(Tasks!$A:$A,A46) -> 4 | O46: =COUNTIFS(Tasks!$A:$A,A46,Tasks!$F:$F,"✓") -> 0 | P46: =IF(N46=0,"",O46/N46) -> 0
A47: 43 | B47: ="L"&IF(A47-'Start here'!$C$7<0,"−","+")&ABS(A47-'Start here'!$C$7) -> L+16 | C47: ='Start here'!$C$6+7*(A47-1) -> 46601 | D47: Phase 2 · New segments | E47: August: lighter cadence | F47: 8–10 h | G47: • Answer questions (about 2 h) | H47: • 1 post | I47: • 1 video | M47: • Prep: Webinar content + a partnership one-pager (users, case studies) | N47: =COUNTIF(Tasks!$A:$A,A47) -> 5 | O47: =COUNTIFS(Tasks!$A:$A,A47,Tasks!$F:$F,"✓") -> 0 | P47: =IF(N47=0,"",O47/N47) -> 0
A48: 44 | B48: ="L"&IF(A48-'Start here'!$C$7<0,"−","+")&ABS(A48-'Start here'!$C$7) -> L+17 | C48: ='Start here'!$C$6+7*(A48-1) -> 46608 | D48: Phase 2 · New segments | E48: Partnerships | F48: 8–10 h | G48: • Answer questions (about 2 h) | H48: • 1 post | I48: • 1 video | M48: • Partnerships: Write to fittings distributors (Blum, Hettich, GTV) and CNC sellers in Romania | N48: =COUNTIF(Tasks!$A:$A,A48) -> 5 | O48: =COUNTIFS(Tasks!$A:$A,A48,Tasks!$F:$F,"✓") -> 0 | P48: =IF(N48=0,"",O48/N48) -> 0
A49: 45 | B49: ="L"&IF(A49-'Start here'!$C$7<0,"−","+")&ABS(A49-'Start here'!$C$7) -> L+18 | C49: ='Start here'!$C$6+7*(A49-1) -> 46615 | D49: Phase 2 · New segments | E49: August: lighter cadence | F49: 8–10 h | G49: • Answer questions (about 2 h) | H49: • 1 post | I49: • 1 video | M49: • Prep: Follow up on partnership replies | N49: =COUNTIF(Tasks!$A:$A,A49) -> 5 | O49: =COUNTIFS(Tasks!$A:$A,A49,Tasks!$F:$F,"✓") -> 0 | P49: =IF(N49=0,"",O49/N49) -> 0
A50: 46 | B50: ="L"&IF(A50-'Start here'!$C$7<0,"−","+")&ABS(A50-'Start here'!$C$7) -> L+19 | C50: ='Start here'!$C$6+7*(A50-1) -> 46622 | D50: Phase 2 · New segments | E50: August: lighter cadence (15 Aug holiday) | F50: 8–10 h | G50: • Answer questions (about 2 h) | H50: • 1 post | I50: • 1 video | N50: =COUNTIF(Tasks!$A:$A,A50) -> 4 | O50: =COUNTIFS(Tasks!$A:$A,A50,Tasks!$F:$F,"✓") -> 0 | P50: =IF(N50=0,"",O50/N50) -> 0
A51: 47 | B51: ="L"&IF(A51-'Start here'!$C$7<0,"−","+")&ABS(A51-'Start here'!$C$7) -> L+20 | C51: ='Start here'!$C$6+7*(A51-1) -> 46629 | D51: Phase 2 · New segments | E51: Manufacturers | F51: 8–10 h | G51: • Answer questions (about 2 h) | H51: • 2 posts this week | M51: • LinkedIn: 5 direct conversations with manufacturers, using the case studies | N51: =COUNTIF(Tasks!$A:$A,A51) -> 4 | O51: =COUNTIFS(Tasks!$A:$A,A51,Tasks!$F:$F,"✓") -> 0 | P51: =IF(N51=0,"",O51/N51) -> 0
A52: 48 | B52: ="L"&IF(A52-'Start here'!$C$7<0,"−","+")&ABS(A52-'Start here'!$C$7) -> L+21 | C52: ='Start here'!$C$6+7*(A52-1) -> 46636 | D52: Phase 2 · New segments | E52: Webinar | F52: 8–10 h | G52: • Answer questions (about 2 h) | H52: • 2 posts this week | M52: • Webinar: Design-school webinar, or a Facebook Live demo | N52: =COUNTIF(Tasks!$A:$A,A52) -> 4 | O52: =COUNTIFS(Tasks!$A:$A,A52,Tasks!$F:$F,"✓") -> 0 | P52: =IF(N52=0,"",O52/N52) -> 0
A53: 49 | B53: ="L"&IF(A53-'Start here'!$C$7<0,"−","+")&ABS(A53-'Start here'!$C$7) -> L+22 | C53: ='Start here'!$C$6+7*(A53-1) -> 46643 | D53: Phase 2 · New segments | E53: Content for designers | F53: 8–10 h | G53: • Answer questions (about 2 h) | H53: • 2 posts this week | I53: • A video for designers | J53: • A post for designers | N53: =COUNTIF(Tasks!$A:$A,A53) -> 5 | O53: =COUNTIFS(Tasks!$A:$A,A53,Tasks!$F:$F,"✓") -> 0 | P53: =IF(N53=0,"",O53/N53) -> 0
A54: 50 | B54: ="L"&IF(A54-'Start here'!$C$7<0,"−","+")&ABS(A54-'Start here'!$C$7) -> L+23 | C54: ='Start here'!$C$6+7*(A54-1) -> 46650 | D54: Phase 2 · New segments | E54: Trade show | F54: 8–10 h | G54: • Answer questions (about 2 h) | H54: • 2 posts this week | M54: • Trade show: BIFE-SIM or a regional fair if the dates fall here: tablet demos, 20–30 conversations | N54: =COUNTIF(Tasks!$A:$A,A54) -> 4 | O54: =COUNTIFS(Tasks!$A:$A,A54,Tasks!$F:$F,"✓") -> 0 | P54: =IF(N54=0,"",O54/N54) -> 0
A55: 51 | B55: ="L"&IF(A55-'Start here'!$C$7<0,"−","+")&ABS(A55-'Start here'!$C$7) -> L+24 | C55: ='Start here'!$C$6+7*(A55-1) -> 46657 | D55: Phase 2 · New segments | E55: Retention set-up | F55: 8–10 h | G55: • Answer questions (about 2 h) | H55: • 2 posts this week | M55: • Retention: Win-back email for cancelled users; plan Founding Partner renewal reminders (April 2028) | N55: =COUNTIF(Tasks!$A:$A,A55) -> 4 | O55: =COUNTIFS(Tasks!$A:$A,A55,Tasks!$F:$F,"✓") -> 0 | P55: =IF(N55=0,"",O55/N55) -> 0
A56: 52 | B56: ="L"&IF(A56-'Start here'!$C$7<0,"−","+")&ABS(A56-'Start here'!$C$7) -> L+25 | C56: ='Start here'!$C$6+7*(A56-1) -> 46664 | D56: Phase 2 · New segments | E56: Year review | F56: 8–10 h | G56: • Answer questions (about 2 h) | H56: • 2 posts this week | M56: • Review: Year review: best channels for confirmed sign-ups and paying users; plan year 2 | N56: =COUNTIF(Tasks!$A:$A,A56) -> 4 | O56: =COUNTIFS(Tasks!$A:$A,A56,Tasks!$F:$F,"✓") -> 0 | P56: =IF(N56=0,"",O56/N56) -> 0

Sheet Tasks
A1: Tasks
A2: Pick ✓ in "Done" when a task is finished. Filter by week or platform with the arrows in row 4.
A4: Week | B4: Week starts | C4: Phase | D4: Platform | E4: Task | F4: Done | G4: Notes
A5: 1 | B5: =INDEX('Weekly plan'!$C:$C,MATCH(A5,'Weekly plan'!$A:$A,0)) -> 46307 | C5: =INDEX('Weekly plan'!$D:$D,MATCH(A5,'Weekly plan'!$A:$A,0)) -> Month -6 · Quiet foundation | D5: Facebook Page | E5: Create the Page: name, wordmark logo, cover, one-line description, link. No posts yet
A6: 1 | B6: =INDEX('Weekly plan'!$C:$C,MATCH(A6,'Weekly plan'!$A:$A,0)) -> 46307 | C6: =INDEX('Weekly plan'!$D:$D,MATCH(A6,'Weekly plan'!$A:$A,0)) -> Month -6 · Quiet foundation | D6: YouTube | E6: Create the channel (profile only, no videos yet)
A7: 1 | B7: =INDEX('Weekly plan'!$C:$C,MATCH(A7,'Weekly plan'!$A:$A,0)) -> 46307 | C7: =INDEX('Weekly plan'!$D:$D,MATCH(A7,'Weekly plan'!$A:$A,0)) -> Month -6 · Quiet foundation | D7: Website | E7: Deploy the coming-soon page (Git/GitHub, Vercel, domain, Brevo, Plausible: see README)
A8: 1 | B8: =INDEX('Weekly plan'!$C:$C,MATCH(A8,'Weekly plan'!$A:$A,0)) -> 46307 | C8: =INDEX('Weekly plan'!$D:$D,MATCH(A8,'Weekly plan'!$A:$A,0)) -> Month -6 · Quiet foundation | D8: Admin | E8: Start SRL registration, Stripe account and e-Factura invoicing (Marketing Plan 4b)
A9: 1 | B9: =INDEX('Weekly plan'!$C:$C,MATCH(A9,'Weekly plan'!$A:$A,0)) -> 46307 | C9: =INDEX('Weekly plan'!$D:$D,MATCH(A9,'Weekly plan'!$A:$A,0)) -> Month -6 · Quiet foundation | D9: Research | E9: List 10–15 groups (search: tâmplari, mobilă la comandă, CNC lemn, proiectare mobilă)
A10: 1 | B10: =INDEX('Weekly plan'!$C:$C,MATCH(A10,'Weekly plan'!$A:$A,0)) -> 46307 | C10: =INDEX('Weekly plan'!$D:$D,MATCH(A10,'Weekly plan'!$A:$A,0)) -> Month -6 · Quiet foundation | D10: Routine | E10: Weekly routine + Friday numbers (see Routine and Weekly numbers)
A11: 2 | B11: =INDEX('Weekly plan'!$C:$C,MATCH(A11,'Weekly plan'!$A:$A,0)) -> 46314 | C11: =INDEX('Weekly plan'!$D:$D,MATCH(A11,'Weekly plan'!$A:$A,0)) -> Month -6 · Quiet foundation | D11: Facebook groups | E11: Join the 5–10 best groups; read each group's rules (links allowed? project mentions?)
A12: 2 | B12: =INDEX('Weekly plan'!$C:$C,MATCH(A12,'Weekly plan'!$A:$A,0)) -> 46314 | C12: =INDEX('Weekly plan'!$D:$D,MATCH(A12,'Weekly plan'!$A:$A,0)) -> Month -6 · Quiet foundation | D12: Facebook groups | E12: Start the question log: every question carpenters ask, word for word
A13: 2 | B13: =INDEX('Weekly plan'!$C:$C,MATCH(A13,'Weekly plan'!$A:$A,0)) -> 46314 | C13: =INDEX('Weekly plan'!$D:$D,MATCH(A13,'Weekly plan'!$A:$A,0)) -> Month -6 · Quiet foundation | D13: Legal | E13: Send the Privacy Policy and Terms drafts to the lawyer (Privacy approval needed by week 12)
A14: 2 | B14: =INDEX('Weekly plan'!$C:$C,MATCH(A14,'Weekly plan'!$A:$A,0)) -> 46314 | C14: =INDEX('Weekly plan'!$D:$D,MATCH(A14,'Weekly plan'!$A:$A,0)) -> Month -6 · Quiet foundation | D14: Routine | E14: Weekly routine + Friday numbers (see Routine and Weekly numbers)
A15: 3 | B15: =INDEX('Weekly plan'!$C:$C,MATCH(A15,'Weekly plan'!$A:$A,0)) -> 46321 | C15: =INDEX('Weekly plan'!$D:$D,MATCH(A15,'Weekly plan'!$A:$A,0)) -> Month -6 · Quiet foundation | D15: Facebook groups | E15: Observe only: tone, recurring pain points, respected voices (anchor-customer candidates)
A16: 3 | B16: =INDEX('Weekly plan'!$C:$C,MATCH(A16,'Weekly plan'!$A:$A,0)) -> 46321 | C16: =INDEX('Weekly plan'!$D:$D,MATCH(A16,'Weekly plan'!$A:$A,0)) -> Month -6 · Quiet foundation | D16: Content | E16: Write 8–10 trade tips for the content bank
... A236: 52 | B236: =INDEX('Weekly plan'!$C:$C,MATCH(A236,'Weekly plan'!$A:$A,0)) -> 46664 | C236: =INDEX('Weekly plan'!$D:$D,MATCH(A236,'Weekly plan'!$A:$A,0)) -> Phase 2 · New segments | D236: Routine | E236: Weekly routine + Friday numbers (see Routine and Weekly numbers)

Sheet Weekly numbers
A1: Weekly numbers
A2: Fill in one row every Friday. Row 5 is an example of the format; the weeks start in row 6.
A4: Week | B4: Week starts | C4: New confirmed sign-ups | D4: Confirmation rate | E4: Sign-ups via invite links | F4: Founding Partner reservations (total) | G4: Questions answered in groups | H4: Facebook Page followers | I4: YouTube subscribers | J4: Blog + Demo page visits | K4: blog_to_signup clicks | L4: Notes
A5: Example | C5: 6 | D5: 0.75 | E5: 1 | G5: 4 | H5: 23 | L5: Format example: replace nothing here, start in row 6
A6: 1 | B6: =INDEX('Weekly plan'!$C:$C,MATCH(A6,'Weekly plan'!$A:$A,0)) -> 46307
A7: 2 | B7: =INDEX('Weekly plan'!$C:$C,MATCH(A7,'Weekly plan'!$A:$A,0)) -> 46314
A8: 3 | B8: =INDEX('Weekly plan'!$C:$C,MATCH(A8,'Weekly plan'!$A:$A,0)) -> 46321
A9: 4 | B9: =INDEX('Weekly plan'!$C:$C,MATCH(A9,'Weekly plan'!$A:$A,0)) -> 46328
A10: 5 | B10: =INDEX('Weekly plan'!$C:$C,MATCH(A10,'Weekly plan'!$A:$A,0)) -> 46335
A11: 6 | B11: =INDEX('Weekly plan'!$C:$C,MATCH(A11,'Weekly plan'!$A:$A,0)) -> 46342
A12: 7 | B12: =INDEX('Weekly plan'!$C:$C,MATCH(A12,'Weekly plan'!$A:$A,0)) -> 46349
A13: 8 | B13: =INDEX('Weekly plan'!$C:$C,MATCH(A13,'Weekly plan'!$A:$A,0)) -> 46356
A14: 9 | B14: =INDEX('Weekly plan'!$C:$C,MATCH(A14,'Weekly plan'!$A:$A,0)) -> 46363
A15: 10 | B15: =INDEX('Weekly plan'!$C:$C,MATCH(A15,'Weekly plan'!$A:$A,0)) -> 46370
A16: 11 | B16: =INDEX('Weekly plan'!$C:$C,MATCH(A16,'Weekly plan'!$A:$A,0)) -> 46377
A17: 12 | B17: =INDEX('Weekly plan'!$C:$C,MATCH(A17,'Weekly plan'!$A:$A,0)) -> 46384
... A57: 52 | B57: =INDEX('Weekly plan'!$C:$C,MATCH(A57,'Weekly plan'!$A:$A,0)) -> 46664

Sheet Website steps
A1: Website steps
A2: One change in src/site.ts or src/config.ts plus a deploy each. Run npm run test:all and npm run check-launch first.
A4: Week | B4: Week starts | C4: Website step | D4: Needs first | E4: Done
A5: 1 | B5: =INDEX('Weekly plan'!$C:$C,MATCH(A5,'Weekly plan'!$A:$A,0)) -> 46307 | C5: Deploy the coming-soon page | D5: Git + GitHub, Vercel account, domain, Brevo setup (README), Plausible
A6: 13 | B6: =INDEX('Weekly plan'!$C:$C,MATCH(A6,'Weekly plan'!$A:$A,0)) -> 46391 | C6: home: true, privacy: true, REFERRAL_PROGRAM = true; rebuild + re-paste emails | D6: Lawyer-approved Privacy Policy (drafts sent week 2, approved by week 12)
A7: 16 | B7: =INDEX('Weekly plan'!$C:$C,MATCH(A7,'Weekly plan'!$A:$A,0)) -> 46412 | C7: foundingPartner: true | D7: BREVO_FP_LIST_ID; open questions 2–3 in DECISIONS.md decided
A8: 18 | B8: =INDEX('Weekly plan'!$C:$C,MATCH(A8,'Weekly plan'!$A:$A,0)) -> 46426 | C8: blog: true + first post published: true | D8: Competitor facts verified (the [VERIFICĂ] markers)
A9: 20 | B9: =INDEX('Weekly plan'!$C:$C,MATCH(A9,'Weekly plan'!$A:$A,0)) -> 46440 | C9: demo: true; video IDs in src/data/demoVideos.ts | D9: The three recorded videos
A10: 21 | B10: =INDEX('Weekly plan'!$C:$C,MATCH(A10,'Weekly plan'!$A:$A,0)) -> 46447 | C10: faq: true; real quotes in src/data/testimonials.ts | D10: Answers to open questions 4–5; testers' written permission
A11: 23 | B11: =INDEX('Weekly plan'!$C:$C,MATCH(A11,'Weekly plan'!$A:$A,0)) -> 46461 | C11: pricing: true, terms: true | D11: Final prices; lawyer-approved Terms
A12: 27 | B12: =INDEX('Weekly plan'!$C:$C,MATCH(A12,'Weekly plan'!$A:$A,0)) -> 46489 | C12: productPublic = true; Founding Partner payments live | D12: Stripe payments built into the site (not built yet: schedule before week 23)

Sheet Deadlines
A1: Deadlines
A2: If one slips, move that week's announcement, not the trust-building work around it.
A4: Needed by week | B4: Week starts | C4: What | D4: Owner | E4: Done
A5: 1 | B5: =INDEX('Weekly plan'!$C:$C,MATCH(A5,'Weekly plan'!$A:$A,0)) -> 46307 | C5: Git + GitHub, Vercel, domain, Brevo setup, Plausible | D5: Founder
A6: 12 | B6: =INDEX('Weekly plan'!$C:$C,MATCH(A6,'Weekly plan'!$A:$A,0)) -> 46384 | C6: Lawyer-approved Privacy Policy (blocks the referral launch) | D6: Lawyer
A7: 14 | B7: =INDEX('Weekly plan'!$C:$C,MATCH(A7,'Weekly plan'!$A:$A,0)) -> 46398 | C7: Product ready for real projects (blocks the private beta) | D7: Founder
A8: 16 | B8: =INDEX('Weekly plan'!$C:$C,MATCH(A8,'Weekly plan'!$A:$A,0)) -> 46412 | C8: Founding Partner open questions 2–3 decided | D8: Founder
A9: 20 | B9: =INDEX('Weekly plan'!$C:$C,MATCH(A9,'Weekly plan'!$A:$A,0)) -> 46440 | C9: Demo videos recorded (weeks 18–20) | D9: Founder
A10: 21 | B10: =INDEX('Weekly plan'!$C:$C,MATCH(A10,'Weekly plan'!$A:$A,0)) -> 46447 | C10: Open questions 4–5 answered (FAQ); testimonial permissions | D10: Founder
A11: 22 | B11: =INDEX('Weekly plan'!$C:$C,MATCH(A11,'Weekly plan'!$A:$A,0)) -> 46454 | C11: Final prices and free-plan limits (open question 1) | D11: Founder
A12: 23 | B12: =INDEX('Weekly plan'!$C:$C,MATCH(A12,'Weekly plan'!$A:$A,0)) -> 46461 | C12: Lawyer-approved Terms | D12: Lawyer
A13: 23 | B13: =INDEX('Weekly plan'!$C:$C,MATCH(A13,'Weekly plan'!$A:$A,0)) -> 46461 | C13: Stripe payments built into the site | D13: Development

Sheet Content bank
A1: Content bank
A2: Facebook Page posts are short: 3–6 lines plus an image or clip. Group content is mostly answers, not posts.
A4: # | B4: Type | C4: Idea | D4: From week | E4: Used in week
A5: 1 | B5: Trade tip | C5: Lățimea pieselor dintre laterale: de ce se scad două grosimi | D5: 5
A6: 2 | B6: Trade tip | C6: Cantul ABS de 2 mm: când și cât scazi din dimensiunea de debitare | D6: 5
A7: 3 | B7: Trade tip | C7: Rosturile ușilor: 2 mm sau 3 mm? Ce iei în calcul | D7: 5
A8: 4 | B8: Trade tip | C8: Balamale aplicate vs. semi-aplicate vs. interioare: diferențele de calcul | D8: 5
A9: 5 | B9: Trade tip | C9: Coliziunea sertar–balama: cum o eviți înainte de tăiere | D9: 5
A10: 6 | B10: Trade tip | C10: Dulapul de colț: trei soluții și dezavantajele fiecăreia | D10: 5
A11: 7 | B11: Trade tip | C11: Cum îți organizezi lista de debitare ca să nu greșești la transcriere | D11: 5
A12: 8 | B12: Trade tip | C12: Optimizarea plăcii: cât material pierzi de obicei și cum reduci | D12: 5
A13: 9 | B13: Trade tip | C13: Ce verifici la un fișier înainte să-l trimiți la CNC | D13: 5
A14: 10 | B14: Trade tip | C14: Cum măsori corect la client: lista de verificare | D14: 5
A15: 11 | B15: Behind the scenes | C15: WIP screenshot: a feature a carpenter in a group asked for | D15: 9
A16: 12 | B16: Behind the scenes | C16: What I learned visiting three workshops | D16: 9
... A30: 26 | B30: Launch | C30: "What we fixed in week 1" | D30: 29

Sheet Routine
A1: Weekly routine
A2: The same every week. Group presence and support are the two things never to cut.
A4: Day | B4: Task | C4: Time
A5: Monday | B5: Facebook groups: answer new questions; update the question log | C5: 45 min
A6: Tuesday | B6: Create this week's Page post or video | C6: 1–2 h
A7: Wednesday | B7: Facebook groups: answers; private conversations (anchor customer, validation) | C7: 45 min
A8: Thursday | B8: Publish (Facebook Page / YouTube / blog) | C8: 30 min
A9: Friday | B9: Fill in "Weekly numbers"; tick off tasks; plan next week | C9: 30 min
A10: Every day | B10: Reply to comments and messages within 24 hours | C10: —
A13: Group etiquette
A14: • | B14: Give value at least 9 times for every 1 mention of Mobilcab.
A15: • | B15: Answer the question asked, fully, even when the honest answer isn't Mobilcab.
A16: • | B16: Never paste the same post in every group on the same day: adapt it, and space it out.
A17: • | B17: Links go in a comment, not the post, if the group allows them at all.
A18: • | B18: If an admin says no, accept it: a ban costs a whole slice of a small market.
